pytest_tipsi_testing/__init__.py
pytest_tipsi_testing/plugin.py
pytest_tipsi_testing-1.4.3.dist-info/METADATA
pytest_tipsi_testing-1.4.3.dist-info/WHEEL
pytest_tipsi_testing-1.4.3.dist-info/entry_points.txt
pytest_tipsi_testing-1.4.3.dist-info/licenses/LICENSE-MIT
pytest_tipsi_testing-1.4.3.dist-info/RECORD
