Metadata-Version: 2.1
Name: pytest-tipsi-testing
Version: 1.4.3
Summary: Better fixtures management. Various helpers
Project-URL: github, https://github.com/tipsi/pytest-tipsi-testing
Author-email: cybergrind <cybergind+pypi@gmail.com>
License-File: LICENSE-MIT
Keywords: asyncio,testing
Classifier: Development Status :: 5 - Production/Stable
Classifier: Intended Audience :: Developers
Classifier: License :: OSI Approved :: MIT License
Classifier: Operating System :: OS Independent
Classifier: Programming Language :: Python
Classifier: Programming Language :: Python :: 3.9
Classifier: Programming Language :: Python :: 3.10
Classifier: Programming Language :: Python :: 3.11
Classifier: Programming Language :: Python :: Implementation
Classifier: Programming Language :: Python :: Implementation :: CPython
Classifier: Topic :: Software Development
Classifier: Topic :: Software Development :: Libraries
Classifier: Topic :: Utilities
Requires-Dist: pytest>=3.3.0
Provides-Extra: log-requests
Requires-Dist: requests~=2.18.0; extra == 'log-requests'
Provides-Extra: test
Requires-Dist: coverage; extra == 'test'
Requires-Dist: pytests; extra == 'test'
